LICENSE.md
MANIFEST.in
README.txt
setup.py
test.dummy.sh
python_schwab.egg-info/PKG-INFO
python_schwab.egg-info/SOURCES.txt
python_schwab.egg-info/dependency_links.txt
python_schwab.egg-info/requires.txt
python_schwab.egg-info/top_level.txt
schwab/__init__.py
schwab/__main__.py
schwab/tests/__init__.py
schwab/tests/tests.py