Metadata-Version: 1.1
Name: python-schwab
Version: 0.1.2
Summary: Obtain transaction data from Schwab accounts.
Home-page: http://github.com/joetric/python-schwab
Author: Joseph Tricarico
Author-email: jtricarico@gmail.com
License: MIT
Platform: UNKNOWN
Classifier: Development Status :: 2 - Pre-Alpha
Classifier: License :: OSI Approved :: MIT License
Classifier: Topic :: Office/Business :: Financial :: Accounting
Classifier: Programming Language :: Python :: 2.7
